etc/runbullet/config.example.yaml
runbullet/__init__.py
runbullet/plugins/__init__.py
runbullet/plugins/.ropeproject/config.py
runbullet/plugins/.ropeproject/globalnames
runbullet/plugins/.ropeproject/history
runbullet/plugins/.ropeproject/objectdb
runbullet/plugins/__pycache__/__init__.cpython-36.pyc
runbullet/plugins/light/__init__.py
runbullet/plugins/music/__init__.py
runbullet/plugins/music/__pycache__/__init__.cpython-36.pyc
runbullet/plugins/music/mpd/__init__.py
runbullet/plugins/music/mpd/__pycache__/__init__.cpython-36.pyc
runbullet/plugins/shell/__init__.py
runbullet-0.2.0.dev1.data/scripts/pusher
runbullet-0.2.0.dev1.dist-info/DESCRIPTION.rst
runbullet-0.2.0.dev1.dist-info/METADATA
runbullet-0.2.0.dev1.dist-info/RECORD
runbullet-0.2.0.dev1.dist-info/WHEEL
runbullet-0.2.0.dev1.dist-info/entry_points.txt
runbullet-0.2.0.dev1.dist-info/metadata.json
runbullet-0.2.0.dev1.dist-info/top_level.txt
