Metadata-Version: 2.0
Name: runbullet
Version: 0.2.0.dev1
Summary: Runbullet service
Home-page: https://github.com/BlackLight/runbullet
Author: Fabio Manganiello
Author-email: info@fabiomanganiello.com
License: MIT
Keywords: pushbullet notifications automation
Platform: UNKNOWN
Classifier: Topic :: Utilities
Classifier: License :: OSI Approved :: MIT License
Classifier: Development Status :: 3 - Alpha
Requires-Python: >= 3
Requires-Dist: pyyaml
